{
  "8306.T": {
    "ind": {
      "ticker": "8306.T",
      "name": "Mitsubishi UFJ Financial Group, Inc.",
      "price": 3600.0,
      "prev_price": 3541.0,
      "change_pct": 1.6661959898333805,
      "ma5": 3489.8,
      "ma25": 3309.0,
      "ma75": 3039.9836328125,
      "rsi": 86.91588785046729,
      "macd": 101.89284328413714,
      "macd_sig": 80.94650708042569,
      "macd_hist": 20.946336203711454,
      "macd_prev": 15.622976178835572,
      "bb_upper": 3566.432894095183,
      "bb_mid": 3338.45,
      "bb_lower": 3110.4671059048164,
      "atr": 77.28571428571429,
      "atr_pct": 2.146825396825397,
      "volume": 53200600.0,
      "volume_ma5": 38723720.0,
      "last_trading_date": "2026-07-14"
    },
    "predictions": {
      "bullish_price": 3677,
      "neutral_range": "3,523〜3,677",
      "bearish_price": 3523,
      "scenario": "下落"
    },
    "cumulative": {
      "win": 8,
      "lose": 41,
      "self_score_sum": 1735,
      "self_score_count": 49,
      "day": 52
    }
  },
  "6758.T": {
    "ind": {
      "ticker": "6758.T",
      "name": "Sony Group Corporation",
      "price": 3383.0,
      "prev_price": 3341.0,
      "change_pct": 1.257108650104759,
      "ma5": 3392.0,
      "ma25": 3309.12,
      "ma75": 3364.6528678385416,
      "rsi": 60.09104704097117,
      "macd": 7.058369007109377,
      "macd_sig": -6.929522670695583,
      "macd_hist": 13.98789167780496,
      "macd_prev": 16.25674134271832,
      "bb_upper": 3510.9987230467223,
      "bb_mid": 3304.35,
      "bb_lower": 3097.7012769532776,
      "atr": 93.78571428571429,
      "atr_pct": 2.7722646847683796,
      "volume": 13640700.0,
      "volume_ma5": 14556760.0,
      "last_trading_date": "2026-07-14"
    },
    "predictions": {
      "bullish_price": 3477,
      "neutral_range": "3289～3477",
      "bearish_price": 3289,
      "scenario": "横ばい"
    },
    "cumulative": {
      "win": 9,
      "lose": 40,
      "self_score_sum": 1770,
      "self_score_count": 49,
      "day": 52
    }
  }
}